ziti_router/__init__.py
ziti_router/cli.py
ziti_router/main.py
ziti_router-0.5.0.dist-info/METADATA
ziti_router-0.5.0.dist-info/WHEEL
ziti_router-0.5.0.dist-info/entry_points.txt
ziti_router-0.5.0.dist-info/top_level.txt
ziti_router-0.5.0.dist-info/RECORD
