Metadata-Version: 2.1
Name: ziti_router
Version: 0.5.0
Summary: A description of your package
Home-page: 
Author: sadath
Author-email: sadathsadu2002@gmail.com
Classifier: Programming Language :: Python :: 3
Classifier: License :: OSI Approved :: MIT License
Classifier: Operating System :: OS Independent
Requires-Python: >=3.6
Requires-Dist: requests
Requires-Dist: pylint
Requires-Dist: pylint-exit
Requires-Dist: pyinstaller
Requires-Dist: tqdm
Requires-Dist: psutil
Requires-Dist: packaging
Requires-Dist: pyjwt
Requires-Dist: colorama
Requires-Dist: jinja2
Requires-Dist: distro
Requires-Dist: pyyaml
